opensitua_core/__init__.py
opensitua_core/compression.py
opensitua_core/datatypes.py
opensitua_core/encryption.py
opensitua_core/execution.py
opensitua_core/filesystem.py
opensitua_core/http.py
opensitua_core/mail.py
opensitua_core/mapfile.py
opensitua_core/platform.py
opensitua_core/stime.py
opensitua_core/strings.py
opensitua_core/xml_utils.py
opensitua_core-0.0.113.dist-info/LICENSE
opensitua_core-0.0.113.dist-info/METADATA
opensitua_core-0.0.113.dist-info/WHEEL
opensitua_core-0.0.113.dist-info/top_level.txt
opensitua_core-0.0.113.dist-info/RECORD
