Metadata-Version: 2.1
Name: opensitua-core
Version: 0.0.113
Summary: A core functions package
Home-page: https://github.com/valluzzi/opensitua_core.git
Author: Valerio Luzzi
Author-email: valluzzi@gmail.com
License: UNKNOWN
Platform: UNKNOWN
Classifier: Programming Language :: Python :: 3
Classifier: License :: OSI Approved :: MIT License
Classifier: Operating System :: OS Independent
License-File: LICENSE
Requires-Dist: jinja2
Requires-Dist: six
Requires-Dist: argparse
Requires-Dist: xmljson
Requires-Dist: openpyxl
Requires-Dist: requests
Requires-Dist: xlrd
Requires-Dist: xlwt
Requires-Dist: xlutils
Requires-Dist: numpy
Requires-Dist: rarfile
Requires-Dist: cryptography
